msys2_wrapper/find_msys2.py
msys2_wrapper/help.py
msys2_wrapper/helper.py
msys2_wrapper/launch_args.py
msys2_wrapper/main.py
msys2_wrapper/parse_args.py
msys2_wrapper/start_shell.py
msys2_wrapper-2025.3.5.1.dist-info/METADATA
msys2_wrapper-2025.3.5.1.dist-info/WHEEL
msys2_wrapper-2025.3.5.1.dist-info/entry_points.txt
msys2_wrapper-2025.3.5.1.dist-info/licenses/LICENSE
msys2_wrapper-2025.3.5.1.dist-info/RECORD
