Metadata-Version: 2.4
Name: msys2-wrapper
Version: 2025.3.5.1
Summary: start msys2 without bat
License-File: LICENSE
Requires-Python: >=3.10
